Metadata-Version: 2.1
Name: envedit
Version: 1.1.0
Summary: A custom Python project to edit environment variables.
Home-page: https://github.com/supercoolin/envedit
Author: Colin Evrard
Author-email: colin.evrard.134@gmail.com
Classifier: Programming Language :: Python :: 3
Classifier: License :: OSI Approved :: MIT License
Classifier: Operating System :: OS Independent
Requires-Python: >=3.10
License-File: LICENSE
